x21e8/__init__.py
x21e8/application/__init__.py
x21e8/application/liquid.py
x21e8/application/notarize.py
x21e8/application/planetmint.py
x21e8/application/rddl.py
x21e8/application/token.py
x21e8/config.py
x21e8/main.py
x21e8/models/__init__.py
x21e8/models/issuing_request.py
x21e8/models/nft_asset.py
x21e8/models/token_related_accounts.py
x21e8/models/transfer.py
x21e8/network/__init__.py
x21e8/network/liquid/__init__.py
x21e8/network/liquid/util.py
x21e8/routers/assets.py
x21e8/routers/config.py
x21e8/routers/data.py
x21e8/routers/machine.py
x21e8/routers/seed.py
x21e8/routers/utils.py
x21e8/routers/wallet.py
x21e8/utils/__init__.py
x21e8/utils/cointype.py
x21e8/utils/eddsa_auth.py
x21e8/utils/encryption.py
x21e8/utils/storage.py
x21e8/wallet/__init__.py
x21e8/wallet/base_wallet.py
x21e8/wallet/planetmint/__init__.py
x21e8/wallet/planetmint/keymanagement.py
x21e8/wallet/planetmint/keystore.py
x21e8/wallet/seed.py
x21e8/wallet/sw_wallet.py
x21e8-0.9.2.dist-info/METADATA
x21e8-0.9.2.dist-info/WHEEL
x21e8-0.9.2.dist-info/RECORD
