Metadata-Version: 2.1
Name: x21e8
Version: 0.9.2
Summary: x21e8 service to manage RDDL network identities on TrustAnchors and workflows.
Author: Firat Berk Cakar
Author-email: firat@riddleandcode.com
Requires-Python: >=3.9,<4.0
Classifier: Programming Language :: Python :: 3
Classifier: Programming Language :: Python :: 3.9
Classifier: Programming Language :: Python :: 3.10
Classifier: Programming Language :: Python :: 3.11
Requires-Dist: TrezorCryptoTestRc
Requires-Dist: bitcoin-utils (>=0.5.6,<0.6.0)
Requires-Dist: fastapi (>=0.85.0,<0.86.0)
Requires-Dist: mnemonic (>=0.20,<0.21)
Requires-Dist: multiformats (>=0.2.1,<0.3.0)
Requires-Dist: mypy (>=0.982,<0.983)
Requires-Dist: planetmint-driver (>=0.18.2,<0.19.0)
Requires-Dist: python-decouple (>=3.6,<4.0)
Requires-Dist: python-rapidjson (>1.0.0)
Requires-Dist: python-rapidjson-schema (==0.1.1)
Requires-Dist: requests (>2.20.0)
Requires-Dist: typing-extensions (==4.5.0)
Requires-Dist: uvicorn (>=0.19.0,<0.20.0)
Requires-Dist: w3storage (>=0.0.1,<0.0.2)
